LICENSE.txt
README.md
hn-compare
setup.py
./logger.py
human_name_compare/__init__.py
human_name_compare.egg-info/PKG-INFO
human_name_compare.egg-info/SOURCES.txt
human_name_compare.egg-info/dependency_links.txt
human_name_compare.egg-info/top_level.txt