Metadata-Version: 2.1
Name: human-name-compare
Version: 0.4.1
Summary: a tool for comparing human names
Home-page: https://github.com/digitalkaoz/py_human_name_compare
Download-URL: https://github.com/digitalkaoz/py_human_name_compare/archive/0.4.1.tar.gz
Author: Robert Schoenthal
Author-email: robert.schoenthal@gmail.com
Keywords: NLP,HUMANNAME
Classifier: Programming Language :: Python :: 3
Classifier: License :: OSI Approved :: MIT License
Classifier: Operating System :: OS Independent
License-File: LICENSE.txt
